{
  "id": "muscat-oman",
  "source": {
    "climateVerified": true,
    "climateVerifiedOn": "2026-04-23",
    "climate": [
      {
        "name": "WeatherSpark",
        "url": "https://weatherspark.com/y/105797/Average-Weather-in-Muscat-Oman-Year-Round"
      }
    ],
    "importedFromCsv": "data/climate/uploads/Climate_Date_07 - Climate Data.csv",
    "scoring": {
      "reviewedOn": "2026-04-23",
      "profile": "seasonality-inference-v1"
    }
  },
  "city": "Muscat",
  "country": "Oman",
  "region": "Muscat Governorate, Gulf of Oman",
  "desc": "Muscat is one of the Gulf's calmer capitals: low-rise, sea-facing and mountain-backed, with whitewashed districts, a striking grand mosque, a long Mutrah waterfront and easy escapes to wadis, forts and desert-edge scenery. It works best for travellers who want winter sun and culture without the vertical-city intensity of Dubai or Doha.",
  "hls": [
    "Sultan Qaboos Grand Mosque",
    "Mutrah Corniche and souq",
    "Hajar mountain backdrop",
    "Wadi day trips",
    "Omani coffee and dates",
    "Warm winter coast"
  ],
  "todo": [
    {
      "name": "Sultan Qaboos Grand Mosque",
      "cat": "Architecture",
      "desc": "Visit outside prayer times and dress appropriately for one of Muscat's signature architectural sights."
    },
    {
      "name": "Mutrah Souq and Corniche",
      "cat": "Market",
      "desc": "Walk the waterfront, then dive into incense, textile and silver lanes in the souq."
    },
    {
      "name": "Royal Opera House area",
      "cat": "Culture",
      "desc": "Check performances or simply use the district for polished modern Omani design."
    },
    {
      "name": "Wadi Shab or Wadi Bani Khalid trip",
      "cat": "Nature",
      "desc": "Plan a full day with swimming gear and careful heat timing for a wadi excursion."
    },
    {
      "name": "Old Muscat and Al Alam Palace area",
      "cat": "City character",
      "desc": "Use the older ceremonial district to see how Muscat shifts from souq bustle to clipped, official sea-facing grandeur."
    },
    {
      "name": "Sunset on Mutrah Fort side",
      "cat": "Views",
      "desc": "Climb above the corniche late in the day for the best look at the harbour curve and the city's softer evening light."
    }
  ],
  "prac": {
    "wifi": {
      "r": 5,
      "spd": "50-140 Mbps",
      "note": "Usually excellent in city hotels, malls and cafe districts, but once you head into wadis, beach coves or mountain roads you should not assume reliable coverage."
    },
    "directGW": false,
    "directFrom": {
      "LGW": false,
      "LCY": false
    },
    "fltNote": "Muscat International is close enough to keep arrivals easy, but the relevant UK reality is Heathrow and hub connections rather than LGW or LCY. Oman Air is currently selling Muscat-London Heathrow flights, so destination-level direct flags stay false only because the UI tracks Gatwick and City. Winter sun demand from late November into March is when fares and better hotels tend to tighten fastest.",
    "airports": [
      {
        "name": "Muscat International Airport",
        "code": "MCT",
        "km": 15,
        "dgw": false,
        "directFrom": {
          "LGW": false,
          "LCY": false
        }
      }
    ],
    "currency": "Omani rial (OMR)",
    "lang": "Arabic; English is common in hotels and transport",
    "tz": "GST (UTC+4)",
    "visa": "British citizens can visit Oman for up to 14 days without a visa, and GOV.UK says your passport must be valid for at least 6 months after arrival. If you want to stay longer, it is better to arrange the appropriate visa online before travel, and border officials may ask for onward travel, accommodation proof and travel health insurance.",
    "bestFor": [
      "Winter sun city breaks",
      "Culture-and-coast trips",
      "Wadi and mountain day trips",
      "Calm Gulf stopovers",
      "First-time Oman itineraries",
      "Low-rise Gulf city breaks"
    ],
    "alerts": [
      "Summer heat can be extreme and limits outdoor sightseeing.",
      "Dress codes matter at mosques and conservative public spaces.",
      "Friday timings and prayer hours can reshape sightseeing plans more than first-time visitors expect.",
      "Wadi trips can be flash-flood sensitive after rain."
    ]
  },
  "sweet": "December to March is usually Muscat's strongest stretch, with genuinely pleasant walking weather, sea-facing evenings that feel good rather than punishing, and the cleanest conditions for mosque, corniche and wadi days.",
  "months": [
    {
      "m": "Jan",
      "avg": 21,
      "hi": 24,
      "lo": 18,
      "daylight": 10.9,
      "cld": 18,
      "rain": 10,
      "busy": 10,
      "ac": 5,
      "fl": 5
    },
    {
      "m": "Feb",
      "avg": 22,
      "hi": 26,
      "lo": 18,
      "daylight": 11.4,
      "cld": 18,
      "rain": 15,
      "busy": 9,
      "ac": 4,
      "fl": 4
    },
    {
      "m": "Mar",
      "avg": 25,
      "hi": 28,
      "lo": 21,
      "daylight": 12.0,
      "cld": 23,
      "rain": 15,
      "busy": 8,
      "ac": 4,
      "fl": 4
    },
    {
      "m": "Apr",
      "avg": 29,
      "hi": 33,
      "lo": 26,
      "daylight": 12.7,
      "cld": 24,
      "rain": 10,
      "busy": 5,
      "ac": 2,
      "fl": 2
    },
    {
      "m": "May",
      "avg": 34,
      "hi": 38,
      "lo": 29,
      "daylight": 13.3,
      "cld": 16,
      "rain": 5,
      "busy": 2,
      "ac": 1,
      "fl": 1
    },
    {
      "m": "Jun",
      "avg": 34,
      "hi": 38,
      "lo": 31,
      "daylight": 13.6,
      "cld": 38,
      "rain": 5,
      "busy": 1,
      "ac": 1,
      "fl": 1
    },
    {
      "m": "Jul",
      "avg": 33,
      "hi": 36,
      "lo": 30,
      "daylight": 13.4,
      "cld": 51,
      "rain": 5,
      "busy": 3,
      "ac": 2,
      "fl": 3
    },
    {
      "m": "Aug",
      "avg": 31,
      "hi": 34,
      "lo": 28,
      "daylight": 12.9,
      "cld": 42,
      "rain": 5,
      "busy": 3,
      "ac": 3,
      "fl": 3
    },
    {
      "m": "Sep",
      "avg": 31,
      "hi": 34,
      "lo": 27,
      "daylight": 12.3,
      "cld": 21,
      "rain": 2,
      "busy": 4,
      "ac": 2,
      "fl": 2
    },
    {
      "m": "Oct",
      "avg": 29,
      "hi": 33,
      "lo": 25,
      "daylight": 11.6,
      "cld": 9,
      "rain": 2,
      "busy": 6,
      "ac": 3,
      "fl": 2
    },
    {
      "m": "Nov",
      "avg": 26,
      "hi": 29,
      "lo": 22,
      "daylight": 11.0,
      "cld": 14,
      "rain": 5,
      "busy": 7,
      "ac": 4,
      "fl": 4
    },
    {
      "m": "Dec",
      "avg": 23,
      "hi": 26,
      "lo": 19,
      "daylight": 10.7,
      "cld": 19,
      "rain": 5,
      "busy": 8,
      "ac": 5,
      "fl": 5
    }
  ]
}
